internlm/__init__.py
internlm/accelerator/__init__.py
internlm/accelerator/abstract_accelerator.py
internlm/accelerator/cuda_accelerator.py
internlm/accelerator/dipu_accelerator.py
internlm/accelerator/npu_accelerator.py
internlm/apis/__init__.py
internlm/apis/inference.py
internlm/checkpoint/__init__.py
internlm/checkpoint/checkpoint_manager.py
internlm/checkpoint/components.py
internlm/checkpoint/load_funcs.py
internlm/checkpoint/utils.py
internlm/core/__init__.py
internlm/core/engine.py
internlm/core/gradient_handler.py
internlm/core/naive_amp.py
internlm/core/trainer.py
internlm/core/context/__init__.py
internlm/core/context/parallel_context.py
internlm/core/context/process_group_initializer.py
internlm/core/context/random.py
internlm/core/parallel/__init__.py
internlm/core/parallel/shard.py
internlm/core/scheduler/__init__.py
internlm/core/scheduler/base_scheduler.py
internlm/core/scheduler/no_pipeline_scheduler.py
internlm/core/scheduler/pipeline_scheduler.py
internlm/core/scheduler/comm/__init__.py
internlm/core/scheduler/comm/p2p.py
internlm/core/scheduler/comm/utils.py
internlm/data/__init__.py
internlm/data/build_dataloader.py
internlm/data/train_state.py
internlm/data/utils.py
internlm/data/tokenized/__init__.py
internlm/data/tokenized/batch_sampler.py
internlm/data/tokenized/collaters.py
internlm/data/tokenized/dataset.py
internlm/data/tokenized/dummy_dataset.py
internlm/data/tokenized/dummy_dataset_multimodal.py
internlm/data/tokenized/packed_dataset.py
internlm/data/tokenized/single_dataset.py
internlm/eval/__init__.py
internlm/eval/evaluation.py
internlm/initialize/__init__.py
internlm/initialize/initialize_tensor.py
internlm/initialize/initialize_trainer.py
internlm/initialize/launch.py
internlm/initialize/legacy/__init__.py
internlm/initialize/legacy/launch.py
internlm/model/__init__.py
internlm/model/builder.py
internlm/model/metrics.py
internlm/model/modeling_internlm.py
internlm/model/modeling_internlm2.py
internlm/model/modeling_llama.py
InternEvo-0.5.2.dist-info/LICENSE
InternEvo-0.5.2.dist-info/METADATA
InternEvo-0.5.2.dist-info/WHEEL
InternEvo-0.5.2.dist-info/top_level.txt
InternEvo-0.5.2.dist-info/RECORD
