Metadata-Version: 2.1
Name: InternEvo
Version: 0.5.2
Summary: an open-sourced lightweight training framework aims to support model pre-training without the need for extensive dependencies
Classifier: Programming Language :: Python :: 3.10
Classifier: Intended Audience :: Developers
Classifier: Intended Audience :: Education
Classifier: Intended Audience :: Science/Research
License-File: LICENSE
Requires-Dist: transformers <4.30.0
Requires-Dist: sentencepiece
Requires-Dist: numpy
Requires-Dist: tqdm
Requires-Dist: psutil
Requires-Dist: packaging
Requires-Dist: pre-commit
Requires-Dist: ninja
Requires-Dist: gputil
Requires-Dist: pytest
Requires-Dist: boto3
Requires-Dist: botocore
Requires-Dist: pyecharts
Requires-Dist: py-libnuma
Requires-Dist: pynvml
Requires-Dist: tensorboard
Requires-Dist: rotary-emb
Requires-Dist: xentropy
